setup.cfg
setup.py
django_hello_sign.egg-info/PKG-INFO
django_hello_sign.egg-info/SOURCES.txt
django_hello_sign.egg-info/dependency_links.txt
django_hello_sign.egg-info/requires.txt
django_hello_sign.egg-info/top_level.txt
hello_sign/__init__.py
hello_sign/admin.py
hello_sign/mixins.py
hello_sign/models.py
hello_sign/services.py
hello_sign/signals.py
hello_sign/urls.py
hello_sign/views.py