Metadata-Version: 1.0
Name: django-hello-sign
Version: 0.1.5
Summary: Django app for integrating with HelloSign
Home-page: https://github.com/rosscdh/django-hello_sign
Author: Ross Crawford-d'Heureuse
Author-email: ross@lawpal.com
License: MIT
Keywords: django hellosign app
Platform: UNKNOWN
